{
 "qt.qt6.623.addons.qt3d.android_x86": {
  "Name": "qt.qt6.623.addons.qt3d.android_x86",
  "DisplayName": "Qt 3D for Android x86",
  "Description": null,
  "Version": "6.2.3-0-202201260832",
  "ReleaseDate": "2022-01-26",
  "AutoDependOn": "qt.qt6.623.addons.qt3d, qt.qt6.623.android_x86",
  "Dependencies": "qt.qt6.623.android_x86",
  "Virtual": "true",
  "Script": "installscript.qs",
  "SortingPriority": null,
  "DownloadableArchives": "qt3d-MacOS-MacOS_10_14-Clang-Android-Android_ANY-X86.7z",
  "CompressedSize": "2.2M",
  "UncompressedSize": "15.1M",
  "SHA1": "4ca2b57e5dc878554ab725cbf0fbd314af840874"
 },
 "qt.qt6.623.addons.qtcharts.android_x86": {
  "Name": "qt.qt6.623.addons.qtcharts.android_x86",
  "DisplayName": "Qt Charts for Android x86",
  "Description": null,
  "Version": "6.2.3-0-202201260832",
  "ReleaseDate": "2022-01-26",
  "AutoDependOn": "qt.qt6.623.addons.qtcharts, qt.qt6.623.android_x86",
  "Dependencies": "qt.qt6.623.android_x86",
  "Virtual": "true",
  "Script": "installscript.qs",
  "SortingPriority": null,
  "DownloadableArchives": "qtcharts-MacOS-MacOS_10_14-Clang-Android-Android_ANY-X86.7z",
  "CompressedSize": "630.1K",
  "UncompressedSize": "4.2M",
  "SHA1": "0f5192ae8c84bdef3d9b92920e12016d13524648"
 },
 "qt.qt6.623.addons.qtconnectivity.android_x86": {
  "Name": "qt.qt6.623.addons.qtconnectivity.android_x86",
  "DisplayName": "Qt Connectivity for Android x86",
  "Description": null,
  "Version": "6.2.3-0-202201260832",
  "ReleaseDate": "2022-01-26",
  "AutoDependOn": "qt.qt6.623.addons.qtconnectivity, qt.qt6.623.android_x86",
  "Dependencies": "qt.qt6.623.android_x86",
  "Virtual": "true",
  "Script": "installscript.qs",
  "SortingPriority": null,
  "DownloadableArchives": "qtconnectivity-MacOS-MacOS_10_14-Clang-Android-Android_ANY-X86.7z",
  "CompressedSize": "279.2K",
  "UncompressedSize": "1.4M",
  "SHA1": "0e32d299fc6ea779548d54d89fd819178f5d29ba"
 },
 "qt.qt6.623.addons.qtdatavis3d.android_x86": {
  "Name": "qt.qt6.623.addons.qtdatavis3d.android_x86",
  "DisplayName": "Qt Data Visualization for Android x86",
  "Description": null,
  "Version": "6.2.3-0-202201260832",
  "ReleaseDate": "2022-01-26",
  "AutoDependOn": "qt.qt6.623.addons.qtdatavis3d, qt.qt6.623.android_x86",
  "Dependencies": "qt.qt6.623.android_x86",
  "Virtual": "true",
  "Script": "installscript.qs",
  "SortingPriority": null,
  "DownloadableArchives": "qtdatavis3d-MacOS-MacOS_10_14-Clang-Android-Android_ANY-X86.7z",
  "CompressedSize": "492.2K",
  "UncompressedSize": "2.8M",
  "SHA1": "3182f246f0e534129b1fd122cda6c08f3e5b7835"
 },
 "qt.qt6.623.addons.qtimageformats.android_x86": {
  "Name": "qt.qt6.623.addons.qtimageformats.android_x86",
  "DisplayName": "Qt Image Formats for Android x86",
  "Description": null,
  "Version": "6.2.3-0-202201260832",
  "ReleaseDate": "2022-01-26",
  "AutoDependOn": "qt.qt6.623.addons.qtimageformats, qt.qt6.623.android_x86",
  "Dependencies": "qt.qt6.623.android_x86",
  "Virtual": "true",
  "Script": "installscript.qs",
  "SortingPriority": null,
  "DownloadableArchives": "qtimageformats-MacOS-MacOS_10_14-Clang-Android-Android_ANY-X86.7z",
  "CompressedSize": "296.4K",
  "UncompressedSize": "912.7K",
  "SHA1": "e188aa7a3613df8affeb89e9e7d5304a4561ed89"
 },
 "qt.qt6.623.addons.qtlottie.android_x86": {
  "Name": "qt.qt6.623.addons.qtlottie.android_x86",
  "DisplayName": "Qt Lottie Animation for Android x86",
  "Description": null,
  "Version": "6.2.3-0-202201260832",
  "ReleaseDate": "2022-01-26",
  "AutoDependOn": "qt.qt6.623.addons.qtlottie, qt.qt6.623.android_x86",
  "Dependencies": "qt.qt6.623.android_x86",
  "Virtual": "true",
  "Script": "installscript.qs",
  "SortingPriority": null,
  "DownloadableArchives": "qtlottie-MacOS-MacOS_10_14-Clang-Android-Android_ANY-X86.7z",
  "CompressedSize": "101.6K",
  "UncompressedSize": "475.1K",
  "SHA1": "8304b3b774c0e45bdfbaa315178dfaf5fde69a74"
 },
 "qt.qt6.623.addons.qtmultimedia.android_x86": {
  "Name": "qt.qt6.623.addons.qtmultimedia.android_x86",
  "DisplayName": "Qt Multimedia for Android x86",
  "Description": null,
  "Version": "6.2.3-0-202201260832",
  "ReleaseDate": "2022-01-26",
  "AutoDependOn": "qt.qt6.623.addons.qtmultimedia, qt.qt6.623.android_x86",
  "Dependencies": "qt.qt6.623.android_x86",
  "Virtual": "true",
  "Script": "installscript.qs",
  "SortingPriority": null,
  "DownloadableArchives": "qtmultimedia-MacOS-MacOS_10_14-Clang-Android-Android_ANY-X86.7z",
  "CompressedSize": "446.3K",
  "UncompressedSize": "2.6M",
  "SHA1": "01ceccd405558d29916e94b6ea1d1eeeaaf09265"
 },
 "qt.qt6.623.addons.qtnetworkauth.android_x86": {
  "Name": "qt.qt6.623.addons.qtnetworkauth.android_x86",
  "DisplayName": "Qt Network Authorization for Android x86",
  "Description": null,
  "Version": "6.2.3-0-202201260832",
  "ReleaseDate": "2022-01-26",
  "AutoDependOn": "qt.qt6.623.addons.qtnetworkauth, qt.qt6.623.android_x86",
  "Dependencies": "qt.qt6.623.android_x86",
  "Virtual": "true",
  "Script": "installscript.qs",
  "SortingPriority": null,
  "DownloadableArchives": "qtnetworkauth-MacOS-MacOS_10_14-Clang-Android-Android_ANY-X86.7z",
  "CompressedSize": "66.3K",
  "UncompressedSize": "311.7K",
  "SHA1": "cceb175e094f4da67b9bc40922138835e9050b74"
 },
 "qt.qt6.623.addons.qtpositioning.android_x86": {
  "Name": "qt.qt6.623.addons.qtpositioning.android_x86",
  "DisplayName": "Qt Positioning for Android x86",
  "Description": null,
  "Version": "6.2.3-0-202201260832",
  "ReleaseDate": "2022-01-26",
  "AutoDependOn": "qt.qt6.623.addons.qtpositioning, qt.qt6.623.android_x86",
  "Dependencies": "qt.qt6.623.android_x86",
  "Virtual": "true",
  "Script": "installscript.qs",
  "SortingPriority": null,
  "DownloadableArchives": "qtpositioning-MacOS-MacOS_10_14-Clang-Android-Android_ANY-X86.7z",
  "CompressedSize": "308.5K",
  "UncompressedSize": "1.6M",
  "SHA1": "dc066a217a0dc6d7a6d724870c2acd9cb3bf63e1"
 },
 "qt.qt6.623.addons.qtremoteobjects.android_x86": {
  "Name": "qt.qt6.623.addons.qtremoteobjects.android_x86",
  "DisplayName": "Qt Remote Objects x86",
  "Description": null,
  "Version": "6.2.3-0-202201260832",
  "ReleaseDate": "2022-01-26",
  "AutoDependOn": "qt.qt6.623.addons.qtremoteobjects, qt.qt6.623.android_x86",
  "Dependencies": "qt.qt6.623.android_x86",
  "Virtual": "true",
  "Script": "installscript.qs",
  "SortingPriority": null,
  "DownloadableArchives": "qtremoteobjects-MacOS-MacOS_10_14-Clang-Android-Android_ANY-X86.7z",
  "CompressedSize": "261.1K",
  "UncompressedSize": "1.4M",
  "SHA1": "7309c6406d2a2121d233b6d4376b658a9114b8f6"
 },
 "qt.qt6.623.addons.qtscxml.android_x86": {
  "Name": "qt.qt6.623.addons.qtscxml.android_x86",
  "DisplayName": "Qt State Machine for Android x86",
  "Description": null,
  "Version": "6.2.3-0-202201260832",
  "ReleaseDate": "2022-01-26",
  "AutoDependOn": "qt.qt6.623.addons.qtscxml, qt.qt6.623.android_x86",
  "Dependencies": "qt.qt6.623.android_x86",
  "Virtual": "true",
  "Script": "installscript.qs",
  "SortingPriority": null,
  "DownloadableArchives": "qtscxml-MacOS-MacOS_10_14-Clang-Android-Android_ANY-X86.7z",
  "CompressedSize": "302.9K",
  "UncompressedSize": "1.7M",
  "SHA1": "fff3650e92ad75f032597b796ac9d3daf27e2d97"
 },
 "qt.qt6.623.addons.qtsensors.android_x86": {
  "Name": "qt.qt6.623.addons.qtsensors.android_x86",
  "DisplayName": "Qt Sensors x86",
  "Description": null,
  "Version": "6.2.3-0-202201260832",
  "ReleaseDate": "2022-01-26",
  "AutoDependOn": "qt.qt6.623.addons.qtsensors, qt.qt6.623.android_x86",
  "Dependencies": "qt.qt6.623.android_x86",
  "Virtual": "true",
  "Script": "installscript.qs",
  "SortingPriority": null,
  "DownloadableArchives": "qtsensors-MacOS-MacOS_10_14-Clang-Android-Android_ANY-X86.7z",
  "CompressedSize": "164.5K",
  "UncompressedSize": "1.2M",
  "SHA1": "9839218d72fd36d14b677ea6cd05d48620f132f8"
 },
 "qt.qt6.623.addons.qtserialbus.android_x86": {
  "Name": "qt.qt6.623.addons.qtserialbus.android_x86",
  "DisplayName": "Qt SerialBus x86",
  "Description": null,
  "Version": "6.2.3-0-202201260832",
  "ReleaseDate": "2022-01-26",
  "AutoDependOn": "qt.qt6.623.addons.qtserialbus, qt.qt6.623.android_x86",
  "Dependencies": "qt.qt6.623.android_x86",
  "Virtual": "true",
  "Script": "installscript.qs",
  "SortingPriority": null,
  "DownloadableArchives": "qtserialbus-MacOS-MacOS_10_14-Clang-Android-Android_ANY-X86.7z",
  "CompressedSize": "143.1K",
  "UncompressedSize": "714.7K",
  "SHA1": "9ee61dc05dc62c4d9903c0e34d227bf982d2f6e8"
 },
 "qt.qt6.623.addons.qtserialport.android_x86": {
  "Name": "qt.qt6.623.addons.qtserialport.android_x86",
  "DisplayName": "Qt SerialPort x86",
  "Description": null,
  "Version": "6.2.3-0-202201260832",
  "ReleaseDate": "2022-01-26",
  "AutoDependOn": "qt.qt6.623.addons.qtserialport, qt.qt6.623.android_x86",
  "Dependencies": "qt.qt6.623.android_x86",
  "Virtual": "true",
  "Script": "installscript.qs",
  "SortingPriority": null,
  "DownloadableArchives": "qtserialport-MacOS-MacOS_10_14-Clang-Android-Android_ANY-X86.7z",
  "CompressedSize": "46.1K",
  "UncompressedSize": "198.4K",
  "SHA1": "03a32b1b6fb380e6df1c2e1cbd428138b10a9a4f"
 },
 "qt.qt6.623.addons.qtvirtualkeyboard.android_x86": {
  "Name": "qt.qt6.623.addons.qtvirtualkeyboard.android_x86",
  "DisplayName": "Qt Virtual Keyboard for Android x86",
  "Description": null,
  "Version": "6.2.3-0-202201260832",
  "ReleaseDate": "2022-01-26",
  "AutoDependOn": "qt.qt6.623.addons.qtvirtualkeyboard, qt.qt6.623.android_x86",
  "Dependencies": "qt.qt6.623.android_x86",
  "Virtual": "true",
  "Script": "installscript.qs",
  "SortingPriority": null,
  "DownloadableArchives": "qtvirtualkeyboard-MacOS-MacOS_10_14-Clang-Android-Android_ANY-X86.7z",
  "CompressedSize": "2.0M",
  "UncompressedSize": "4.6M",
  "SHA1": "90622367e69c3426dbcb890a97f50e9ca3813c37"
 },
 "qt.qt6.623.addons.qtwebchannel.android_x86": {
  "Name": "qt.qt6.623.addons.qtwebchannel.android_x86",
  "DisplayName": "Qt WebChannel for Android x86",
  "Description": null,
  "Version": "6.2.3-0-202201260832",
  "ReleaseDate": "2022-01-26",
  "AutoDependOn": "qt.qt6.623.addons.qtwebchannel, qt.qt6.623.android_x86",
  "Dependencies": "qt.qt6.623.android_x86",
  "Virtual": "true",
  "Script": "installscript.qs",
  "SortingPriority": null,
  "DownloadableArchives": "qtwebchannel-MacOS-MacOS_10_14-Clang-Android-Android_ANY-X86.7z",
  "CompressedSize": "83.6K",
  "UncompressedSize": "363.7K",
  "SHA1": "49799a942c536ffd2dfd22b4ecb1636447533173"
 },
 "qt.qt6.623.addons.qtwebsockets.android_x86": {
  "Name": "qt.qt6.623.addons.qtwebsockets.android_x86",
  "DisplayName": "Qt WebSockets for Android x86",
  "Description": null,
  "Version": "6.2.3-0-202201260832",
  "ReleaseDate": "2022-01-26",
  "AutoDependOn": "qt.qt6.623.addons.qtwebsockets, qt.qt6.623.android_x86",
  "Dependencies": "qt.qt6.623.android_x86",
  "Virtual": "true",
  "Script": "installscript.qs",
  "SortingPriority": null,
  "DownloadableArchives": "qtwebsockets-MacOS-MacOS_10_14-Clang-Android-Android_ANY-X86.7z",
  "CompressedSize": "86.5K",
  "UncompressedSize": "419.4K",
  "SHA1": "76172c647edf54815361f21df33d3fcf86ce51e6"
 },
 "qt.qt6.623.addons.qtwebview.android_x86": {
  "Name": "qt.qt6.623.addons.qtwebview.android_x86",
  "DisplayName": "Qt WebView for Android x86",
  "Description": null,
  "Version": "6.2.3-0-202201260832",
  "ReleaseDate": "2022-01-26",
  "AutoDependOn": "qt.qt6.623.addons.qtwebview, qt.qt6.623.android_x86",
  "Dependencies": "qt.qt6.623.android_x86",
  "Virtual": "true",
  "Script": "installscript.qs",
  "SortingPriority": null,
  "DownloadableArchives": "qtwebview-MacOS-MacOS_10_14-Clang-Android-Android_ANY-X86.7z",
  "CompressedSize": "74.4K",
  "UncompressedSize": "350.5K",
  "SHA1": "ae819e83933a3752b8f8bcd15416e0d846bdf6f8"
 },
 "qt.qt6.623.android_x86": {
  "Name": "qt.qt6.623.android_x86",
  "DisplayName": "Android x86",
  "Description": "Qt 6.2.3 Prebuilt Components for Android x86",
  "Version": "6.2.3-0-202201260832",
  "ReleaseDate": "2022-01-26",
  "Dependencies": "qt.tools.qtcreator, qt.qt6.623.doc, qt.qt6.623.examples",
  "AutoDependOn": null,
  "Virtual": "true",
  "Script": "installscript.qs",
  "SortingPriority": "250",
  "DownloadableArchives": "qtbase-MacOS-MacOS_10_14-Clang-Android-Android_ANY-X86.7z, qtsvg-MacOS-MacOS_10_14-Clang-Android-Android_ANY-X86.7z, qtdeclarative-MacOS-MacOS_10_14-Clang-Android-Android_ANY-X86.7z, qttools-MacOS-MacOS_10_14-Clang-Android-Android_ANY-X86.7z, qttranslations-MacOS-MacOS_10_14-Clang-Android-Android_ANY-X86.7z",
  "CompressedSize": "41.2M",
  "UncompressedSize": "314.8M",
  "SHA1": "f1af013bfcc1e51ef241ff7c369512d3ee3ef10c",
  "ArchiveSizes": {
   "qttranslations-MacOS-MacOS_10_14-Clang-Android-Android_ANY-X86.7z": "1.6M",
   "qttools-MacOS-MacOS_10_14-Clang-Android-Android_ANY-X86.7z": "3.5M",
   "qtsvg-MacOS-MacOS_10_14-Clang-Android-Android_ANY-X86.7z": "137K",
   "qtdeclarative-MacOS-MacOS_10_14-Clang-Android-Android_ANY-X86.7z": "24M",
   "qtbase-MacOS-MacOS_10_14-Clang-Android-Android_ANY-X86.7z": "12M"
  }
 },
 "qt.qt6.623.qt5compat.android_x86": {
  "Name": "qt.qt6.623.qt5compat.android_x86",
  "DisplayName": "Qt 5 Compatibility Module for Android x86",
  "Description": null,
  "Version": "6.2.3-0-202201260832",
  "ReleaseDate": "2022-01-26",
  "AutoDependOn": "qt.qt6.623.qt5compat, qt.qt6.623.android_x86",
  "Dependencies": "qt.qt6.623.android_x86",
  "Virtual": "true",
  "Script": "installscript.qs",
  "SortingPriority": null,
  "DownloadableArchives": "qt5compat-MacOS-MacOS_10_14-Clang-Android-Android_ANY-X86.7z",
  "CompressedSize": "513.6K",
  "UncompressedSize": "1.6M",
  "SHA1": "7d9dbae6256631940b594755df659aa609f90931"
 },
 "qt.qt6.623.qtquick3d.android_x86": {
  "Name": "qt.qt6.623.qtquick3d.android_x86",
  "DisplayName": "Qt Quick 3D for Android x86",
  "Description": null,
  "Version": "6.2.3-0-202201260832",
  "ReleaseDate": "2022-01-26",
  "AutoDependOn": "qt.qt6.623.qtquick3d, qt.qt6.623.android_x86",
  "Dependencies": "qt.qt6.623.android_x86",
  "Virtual": "true",
  "Script": "installscript.qs",
  "SortingPriority": null,
  "DownloadableArchives": "qtquick3d-MacOS-MacOS_10_14-Clang-Android-Android_ANY-X86.7z",
  "CompressedSize": "1.2M",
  "UncompressedSize": "6.2M",
  "SHA1": "da593cf9181ad570f328401317af43513304c2ee"
 },
 "qt.qt6.623.qtquicktimeline.android_x86": {
  "Name": "qt.qt6.623.qtquicktimeline.android_x86",
  "DisplayName": "Qt Quick Timeline for Android x86",
  "Description": null,
  "Version": "6.2.3-0-202201260832",
  "ReleaseDate": "2022-01-26",
  "AutoDependOn": "qt.qt6.623.qtquicktimeline, qt.qt6.623.android_x86",
  "Dependencies": "qt.qt6.623.android_x86",
  "Virtual": "true",
  "Script": "installscript.qs",
  "SortingPriority": null,
  "DownloadableArchives": "qtquicktimeline-MacOS-MacOS_10_14-Clang-Android-Android_ANY-X86.7z",
  "CompressedSize": "40.5K",
  "UncompressedSize": "195.0K",
  "SHA1": "78e2d24c5f7d4807b80a879dfc83301da2a8aa52"
 },
 "qt.qt6.623.qtshadertools.android_x86": {
  "Name": "qt.qt6.623.qtshadertools.android_x86",
  "DisplayName": "Qt Shader Tools for Android x86",
  "Description": null,
  "Version": "6.2.3-0-202201260832",
  "ReleaseDate": "2022-01-26",
  "AutoDependOn": "qt.qt6.623.qtshadertools, qt.qt6.623.android_x86",
  "Dependencies": "qt.qt6.623.android_x86",
  "Virtual": "true",
  "Script": "installscript.qs",
  "SortingPriority": null,
  "DownloadableArchives": "qtshadertools-MacOS-MacOS_10_14-Clang-Android-Android_ANY-X86.7z",
  "CompressedSize": "921.6K",
  "UncompressedSize": "3.5M",
  "SHA1": "f6efffaeb6414b5eef8cf65a20c1aa99a63b7f14"
 }
}