{
 "qt.qt6.680": {
  "Name": "qt.qt6.680",
  "DisplayName": "Qt 6.8.0-beta4",
  "Description": "Qt 6.8.0-beta4 <br><br>sha1: 6a340438f846ccd165350c7c6786cb4059014029",
  "Version": "6.8.0-0-202408290438",
  "ReleaseDate": "2024-08-29",
  "Script": "installscript.qs",
  "Dependencies": "qt.qt6.680.doc, qt.qt6.680.examples, qt.tools.qtcreator",
  "AutoDependOn": null,
  "Virtual": "false",
  "SortingPriority": "60800",
  "DownloadableArchives": "sha1s.txt.7z",
  "CompressedSize": "1.6K",
  "UncompressedSize": "2.3K",
  "SHA1": "a65efa2950a5ef1395e89452b7259089748c81c8"
 },
 "qt.qt6.680.doc": {
  "Name": "qt.qt6.680.doc",
  "DisplayName": "Qt 6.8.0 Documentation",
  "Description": "Qt 6.8.0 documentation",
  "Version": "6.8.0-0-202408290438",
  "ReleaseDate": "2024-08-29",
  "Dependencies": "qt.tools",
  "Virtual": "true",
  "Script": "installscript.qs",
  "SortingPriority": "1",
  "DownloadableArchives": "qt5-documentation.zip, qdoc-documentation.zip, qmake-documentation.zip, qtassistant-documentation.zip, qtconcurrent-documentation.zip, qtcmake-documentation.zip, qtcore-documentation.zip, qtdbus-documentation.zip, qtdesigner-documentation.zip, qtdistancefieldgenerator-documentation.zip, qtdoc-documentation.zip, qtgui-documentation.zip, qthelp-documentation.zip, qtlabsplatform-documentation.zip, qtlinguist-documentation.zip, qtnetwork-documentation.zip, qtopengl-documentation.zip, qtplatformintegration-documentation.zip, qtprintsupport-documentation.zip, qtqml-documentation.zip, qtqmlcore-documentation.zip, qtqmlmodels-documentation.zip, qtqmltest-documentation.zip, qtqmlworkerscript-documentation.zip, qtqmlxmllistmodel-documentation.zip, qtquick-documentation.zip, qtquickcontrols-documentation.zip, qtquickdialogs-documentation.zip, qtsql-documentation.zip, qtsvg-documentation.zip, qttestlib-documentation.zip, qtuitools-documentation.zip, qtwaylandcompositor-documentation.zip, qtwidgets-documentation.zip, qtxml-documentation.zip",
  "CompressedSize": "104.2M",
  "UncompressedSize": "213.2M",
  "SHA1": "ae592109f94bab8deae5f15ea43822b203681765",
  "ArchiveSizes": {}
 },
 "qt.qt6.680.doc.qt3d": {
  "Name": "qt.qt6.680.doc.qt3d",
  "DisplayName": "Documentation for Qt 6.8.0 Qt 3D",
  "Description": "Documentation for Qt 6.8.0 Qt 3D",
  "Version": "6.8.0-0-202408290438",
  "ReleaseDate": "2024-08-29",
  "Virtual": "true",
  "SortingPriority": "1",
  "DownloadableArchives": "qt3d-documentation.zip",
  "CompressedSize": "7.4M",
  "UncompressedSize": "19.8M",
  "SHA1": "ee833afa72b37972cdb8308e3443f0639223f71e"
 },
 "qt.qt6.680.doc.qt5compat": {
  "Name": "qt.qt6.680.doc.qt5compat",
  "DisplayName": "Documentation for Qt 6.8.0 Qt 5 Compatibility Module",
  "Description": "Documentation for Qt 6.8.0 Qt 5 Compatibility Module",
  "Version": "6.8.0-0-202408290438",
  "ReleaseDate": "2024-08-29",
  "Virtual": "true",
  "SortingPriority": "1",
  "DownloadableArchives": "qtcore5compat-documentation.zip, qtgraphicaleffects5compat-documentation.zip",
  "CompressedSize": "30.0M",
  "UncompressedSize": "32.3M",
  "SHA1": "6bc41ed9fde95037945eeeabbfac67b7340154e5",
  "ArchiveSizes": {}
 },
 "qt.qt6.680.doc.qtactiveqt": {
  "Name": "qt.qt6.680.doc.qtactiveqt",
  "DisplayName": "Documentation for Qt 6.8.0 Qt 3D",
  "Description": "Documentation for Qt 6.8.0 Qt 3D",
  "Version": "6.8.0-0-202408290438",
  "ReleaseDate": "2024-08-29",
  "Virtual": "true",
  "SortingPriority": "1",
  "DownloadableArchives": "activeqt-documentation.zip",
  "CompressedSize": "362.4K",
  "UncompressedSize": "1.3M",
  "SHA1": "f1cc146c0da147c0d3fe047d3d0c187839b972fd"
 },
 "qt.qt6.680.doc.qtbluetooth": {
  "Name": "qt.qt6.680.doc.qtbluetooth",
  "DisplayName": "Documentation for Qt 6.8.0 GPLv3 components (QtConnectivity/Bluetooth)",
  "Description": "Documentation for Qt 6.8.0 GPLv3 components (QtConnectivity/Bluetooth)",
  "Version": "6.8.0-0-202408290438",
  "ReleaseDate": "2024-08-29",
  "Virtual": "true",
  "SortingPriority": "1",
  "DownloadableArchives": "qtbluetooth-documentation.zip",
  "CompressedSize": "1.2M",
  "UncompressedSize": "3.1M",
  "SHA1": "024fb6721e81b0cb9c186d9aa6e46a28699ddebc"
 },
 "qt.qt6.680.doc.qtcharts": {
  "Name": "qt.qt6.680.doc.qtcharts",
  "DisplayName": "Documentation for Qt 6.8.0 GPLv3 components (QtCharts)",
  "Description": "Documentation for Qt 6.8.0 GPLv3 components (QtCharts)",
  "Version": "6.8.0-0-202408290438",
  "ReleaseDate": "2024-08-29",
  "Virtual": "true",
  "SortingPriority": "1",
  "DownloadableArchives": "qtcharts-documentation.zip",
  "CompressedSize": "9.3M",
  "UncompressedSize": "14.2M",
  "SHA1": "e8425f84f361a53900bf71b452d7d64d83f11b23"
 },
 "qt.qt6.680.doc.qtdatavis3d": {
  "Name": "qt.qt6.680.doc.qtdatavis3d",
  "DisplayName": "Documentation for Qt 6.8.0 GPLv3 components (QtDataVisualization)",
  "Description": "Documentation for Qt 6.8.0 GPLv3 components (QtDataVisualization)",
  "Version": "6.8.0-0-202408290438",
  "ReleaseDate": "2024-08-29",
  "Virtual": "true",
  "SortingPriority": "1",
  "DownloadableArchives": "qtdatavis3d-documentation.zip",
  "CompressedSize": "3.4M",
  "UncompressedSize": "7.0M",
  "SHA1": "9f9b380462fb29a42697ecdb98b5f125fc90a86d"
 },
 "qt.qt6.680.doc.qtgraphs": {
  "Name": "qt.qt6.680.doc.qtgraphs",
  "DisplayName": "Documentation for Qt 6.8.0 GPLv3 components (QtGraphs)",
  "Description": "Documentation for Qt 6.8.0 GPLv3 components (QtGraphs)",
  "Version": "6.8.0-0-202408290438",
  "ReleaseDate": "2024-08-29",
  "Virtual": "true",
  "SortingPriority": "1",
  "DownloadableArchives": "qtgraphs-documentation.zip",
  "CompressedSize": "4.6M",
  "UncompressedSize": "10.1M",
  "SHA1": "e89cb332f0978928a7c66b60c5576c4982f1d7c9"
 },
 "qt.qt6.680.doc.qtgrpc": {
  "Name": "qt.qt6.680.doc.qtgrpc",
  "DisplayName": "Documentation for Qt 6.8.0 Qt Protobuf and Qt GRPC",
  "Description": "Documentation for Qt 6.8.0 Qt Protobuf and Qt GRPC",
  "Version": "6.8.0-0-202408290438",
  "ReleaseDate": "2024-08-29",
  "Virtual": "true",
  "SortingPriority": "1",
  "DownloadableArchives": "qtprotobuf-documentation.zip, qtgrpc-documentation.zip",
  "CompressedSize": "779.4K",
  "UncompressedSize": "1.7M",
  "SHA1": "592fdf7759785a0c609191dbb3fddd3675a41e15",
  "ArchiveSizes": {}
 },
 "qt.qt6.680.doc.qthttpserver": {
  "Name": "qt.qt6.680.doc.qthttpserver",
  "DisplayName": "Documentation for Qt 6.8.0 HTTP Server",
  "Description": "Documentation for Qt 6.8.0 HTTP Server ",
  "Version": "6.8.0-0-202408290438",
  "ReleaseDate": "2024-08-29",
  "Virtual": "true",
  "SortingPriority": "1",
  "DownloadableArchives": "qthttpserver-documentation.zip",
  "CompressedSize": "378.6K",
  "UncompressedSize": "1.0M",
  "SHA1": "4d800df07a8bb0f557a4664ac3b65da036f088ce"
 },
 "qt.qt6.680.doc.qtimageformats": {
  "Name": "qt.qt6.680.doc.qtimageformats",
  "DisplayName": "Documentation for Qt 6.8.0 Imageformats",
  "Description": "Documentation for Qt 6.8.0 Imageformats",
  "Version": "6.8.0-0-202408290438",
  "ReleaseDate": "2024-08-29",
  "Virtual": "true",
  "SortingPriority": "1",
  "DownloadableArchives": "qtimageformats-documentation.zip",
  "CompressedSize": "49.1K",
  "UncompressedSize": "138.6K",
  "SHA1": "246239abe6b1b26bf9e5fccab8574347b90dfbf2"
 },
 "qt.qt6.680.doc.qtlocation": {
  "Name": "qt.qt6.680.doc.qtlocation",
  "DisplayName": "Documentation for Qt 6.8.0 Location",
  "Description": "Documentation for Qt 6.8.0 Location",
  "Version": "6.8.0-0-202408290438",
  "ReleaseDate": "2024-08-29",
  "Virtual": "true",
  "SortingPriority": "1",
  "DownloadableArchives": "qtlocation-documentation.zip",
  "CompressedSize": "4.2M",
  "UncompressedSize": "6.9M",
  "SHA1": "331029fcbb235917dab6e10403f273a778f8e254"
 },
 "qt.qt6.680.doc.qtlottie": {
  "Name": "qt.qt6.680.doc.qtlottie",
  "DisplayName": "Documentation for Qt 6.8.0 Lottie Animation",
  "Description": "Documentation for Qt 6.8.0 Lottie Animation",
  "Version": "6.8.0-0-202408290438",
  "ReleaseDate": "2024-08-29",
  "Virtual": "true",
  "SortingPriority": "1",
  "DownloadableArchives": "qtlottieanimation-documentation.zip",
  "CompressedSize": "59.9K",
  "UncompressedSize": "190.5K",
  "SHA1": "4bbaef4446724a7b206e9450e881dab3be11dd74"
 },
 "qt.qt6.680.doc.qtmultimedia": {
  "Name": "qt.qt6.680.doc.qtmultimedia",
  "DisplayName": "Documentation for Qt Multimedia",
  "Description": "Documentation for Qt Multimedia",
  "Version": "6.8.0-0-202408290438",
  "ReleaseDate": "2024-08-29",
  "Virtual": "true",
  "SortingPriority": "1",
  "DownloadableArchives": "qtmultimedia-documentation.zip, qtspatialaudio-documentation.zip",
  "CompressedSize": "6.0M",
  "UncompressedSize": "9.4M",
  "SHA1": "9b8fe8540882f22cd8ea1f72bde440aaccadb930",
  "ArchiveSizes": {}
 },
 "qt.qt6.680.doc.qtnetworkauth": {
  "Name": "qt.qt6.680.doc.qtnetworkauth",
  "DisplayName": "Documentation for Qt Networkauth (Technology Preview)",
  "Description": "Documentation for Qt Networkauth (Technology Preview)",
  "Version": "6.8.0-0-202408290438",
  "ReleaseDate": "2024-08-29",
  "Virtual": "true",
  "SortingPriority": "1",
  "DownloadableArchives": "qtnetworkauth-documentation.zip",
  "CompressedSize": "475.4K",
  "UncompressedSize": "1.1M",
  "SHA1": "1e77c881c5192155ffa9502a531e12464cdcae5f"
 },
 "qt.qt6.680.doc.qtnfc": {
  "Name": "qt.qt6.680.doc.qtnfc",
  "DisplayName": "Documentation for Qt 6.8.0 GPLv3 components (QtConnectivity/NFC)",
  "Description": "Documentation for Qt 6.8.0 GPLv3 components (QtConnectivity/NFC)",
  "Version": "6.8.0-0-202408290438",
  "ReleaseDate": "2024-08-29",
  "Virtual": "true",
  "SortingPriority": "1",
  "DownloadableArchives": "qtnfc-documentation.zip",
  "CompressedSize": "311.1K",
  "UncompressedSize": "858.3K",
  "SHA1": "55a425b18980273f605c76be05806f2fb2c411e4"
 },
 "qt.qt6.680.doc.qtpositioning": {
  "Name": "qt.qt6.680.doc.qtpositioning",
  "DisplayName": "Documentation for Qt 6.8.0 GPLv3 components (QtPositioning)",
  "Description": "Documentation for Qt 6.8.0 GPLv3 components (QtPositioning)",
  "Version": "6.8.0-0-202408290438",
  "ReleaseDate": "2024-08-29",
  "Virtual": "true",
  "SortingPriority": "1",
  "DownloadableArchives": "qtpositioning-documentation.zip",
  "CompressedSize": "922.4K",
  "UncompressedSize": "2.3M",
  "SHA1": "be1de1e8fd40639d1eccceaa7b64cac89d14c64b"
 },
 "qt.qt6.680.doc.qtquick3d": {
  "Name": "qt.qt6.680.doc.qtquick3d",
  "DisplayName": "Documentation for Qt 6.8.0 GPLv3 components (QtQuick3D)",
  "Description": "Documentation for Qt 6.8.0 GPLv3 components (QtQuick3D)",
  "Version": "6.8.0-0-202408290438",
  "ReleaseDate": "2024-08-29",
  "Virtual": "true",
  "SortingPriority": "1",
  "DownloadableArchives": "qtquick3d-documentation.zip",
  "CompressedSize": "50.8M",
  "UncompressedSize": "56.8M",
  "SHA1": "188bb2c40231507d441c7d4fbc35d6a969ddd781"
 },
 "qt.qt6.680.doc.qtquick3dphysics": {
  "Name": "qt.qt6.680.doc.qtquick3dphysics",
  "DisplayName": "Documentation for Qt 6.8.0 Quick: 3D Physics",
  "Description": "Documentation for Qt 6.8.0 Quick: 3D Physics ",
  "Version": "6.8.0-0-202408290438",
  "ReleaseDate": "2024-08-29",
  "Virtual": "true",
  "SortingPriority": "1",
  "DownloadableArchives": "qtquick3dphysics-documentation.zip",
  "CompressedSize": "5.0M",
  "UncompressedSize": "5.9M",
  "SHA1": "2c499f52108659635b7e586c9a4017422015e83a"
 },
 "qt.qt6.680.doc.qtquickeffectmaker": {
  "Name": "qt.qt6.680.doc.qtquickeffectmaker",
  "DisplayName": "Documentation for Qt 6.8.0 Quick Effect Maker",
  "Description": "Documentation for Qt 6.8.0 Quick Effect Maker",
  "Version": "6.8.0-0-202408290438",
  "ReleaseDate": "2024-08-29",
  "Virtual": "true",
  "SortingPriority": "1",
  "DownloadableArchives": "qtquickeffectmaker-documentation.zip",
  "CompressedSize": "927.7K",
  "UncompressedSize": "1.1M",
  "SHA1": "ba90552948f174159b333e5b707a8f777966947b"
 },
 "qt.qt6.680.doc.qtquicktimeline": {
  "Name": "qt.qt6.680.doc.qtquicktimeline",
  "DisplayName": "Documentation for Qt Quick Timeline",
  "Description": "Documentation for Qt Quick Timeline",
  "Version": "6.8.0-0-202408290438",
  "ReleaseDate": "2024-08-29",
  "Virtual": "true",
  "SortingPriority": "1",
  "DownloadableArchives": "qtquicktimeline-documentation.zip",
  "CompressedSize": "205.8K",
  "UncompressedSize": "375.0K",
  "SHA1": "b0b4fbb41ee44d5f243d4f6e094cd9e7c8d00426"
 },
 "qt.qt6.680.doc.qtremoteobjects": {
  "Name": "qt.qt6.680.doc.qtremoteobjects",
  "DisplayName": "Documentation for Qt Remote Objects",
  "Description": "Documentation for Qt Remote Objects",
  "Version": "6.8.0-0-202408290438",
  "ReleaseDate": "2024-08-29",
  "Virtual": "true",
  "SortingPriority": "1",
  "DownloadableArchives": "qtremoteobjects-documentation.zip",
  "CompressedSize": "671.0K",
  "UncompressedSize": "1.5M",
  "SHA1": "328b4ce618405af62a679f797ff3f40c584c93f3"
 },
 "qt.qt6.680.doc.qtscxml": {
  "Name": "qt.qt6.680.doc.qtscxml",
  "DisplayName": "Documentation for Qt 6.8.0 SCXML",
  "Description": "Documentation for Qt 6.8.0 SCXML",
  "Version": "6.8.0-0-202408290438",
  "ReleaseDate": "2024-08-29",
  "Virtual": "true",
  "SortingPriority": "1",
  "DownloadableArchives": "qtscxml-documentation.zip, qtstatemachine-documentation.zip",
  "CompressedSize": "1.1M",
  "UncompressedSize": "2.9M",
  "SHA1": "1cf39c9ed941e1e3c1f2b59af30e0e37ff93ddf2",
  "ArchiveSizes": {}
 },
 "qt.qt6.680.doc.qtsensors": {
  "Name": "qt.qt6.680.doc.qtsensors",
  "DisplayName": "Documentation for Qt 6.8.0 Sensors",
  "Description": "Documentation for Qt 6.8.0 Sensors",
  "Version": "6.8.0-0-202408290438",
  "ReleaseDate": "2024-08-29",
  "Virtual": "true",
  "SortingPriority": "1",
  "DownloadableArchives": "qtsensors-documentation.zip",
  "CompressedSize": "2.4M",
  "UncompressedSize": "4.1M",
  "SHA1": "b86b00de430a6f178eb06802f0135334b32a0688"
 },
 "qt.qt6.680.doc.qtserialbus": {
  "Name": "qt.qt6.680.doc.qtserialbus",
  "DisplayName": "Documentation for Qt 6.8.0 SerialBus",
  "Description": "Documentation for Qt 6.8.0 SerialBus",
  "Version": "6.8.0-0-202408290438",
  "ReleaseDate": "2024-08-29",
  "Virtual": "true",
  "SortingPriority": "1",
  "DownloadableArchives": "qtserialbus-documentation.zip",
  "CompressedSize": "914.8K",
  "UncompressedSize": "2.3M",
  "SHA1": "2259e8e503e4a5042abc6863686159cb63c6856d"
 },
 "qt.qt6.680.doc.qtserialport": {
  "Name": "qt.qt6.680.doc.qtserialport",
  "DisplayName": "Documentation for Qt 6.8.0 SerialPort",
  "Description": "Documentation for Qt 6.8.0 SerialPort",
  "Version": "6.8.0-0-202408290438",
  "ReleaseDate": "2024-08-29",
  "Virtual": "true",
  "SortingPriority": "1",
  "DownloadableArchives": "qtserialport-documentation.zip",
  "CompressedSize": "221.5K",
  "UncompressedSize": "542.6K",
  "SHA1": "96b3aed366de8836d7ff1fff0196df1798968f2b"
 },
 "qt.qt6.680.doc.qtshadertools": {
  "Name": "qt.qt6.680.doc.qtshadertools",
  "DisplayName": "Documentation for Qt 6.8.0 Qt Shader Tools",
  "Description": "Documentation for Qt 6.8.0 Qt Shader Tools",
  "Version": "6.8.0-0-202408290438",
  "ReleaseDate": "2024-08-29",
  "Virtual": "true",
  "SortingPriority": "1",
  "DownloadableArchives": "qtshadertools-documentation.zip",
  "CompressedSize": "229.6K",
  "UncompressedSize": "470.0K",
  "SHA1": "d4ef61dad42136c44ce3a9a41abd3d9ec74f815b"
 },
 "qt.qt6.680.doc.qtspeech": {
  "Name": "qt.qt6.680.doc.qtspeech",
  "DisplayName": "Documentation for Qt Speech (Technology Preview)",
  "Description": "Documentation for Qt Speech (Technology Preview)",
  "Version": "6.8.0-0-202408290438",
  "ReleaseDate": "2024-08-29",
  "Virtual": "true",
  "SortingPriority": "1",
  "DownloadableArchives": "qttexttospeech-documentation.zip",
  "CompressedSize": "447.5K",
  "UncompressedSize": "796.6K",
  "SHA1": "5ab78f39b169595dbc2781072bc63d1cdd2235b1"
 },
 "qt.qt6.680.doc.qtvirtualkeyboard": {
  "Name": "qt.qt6.680.doc.qtvirtualkeyboard",
  "DisplayName": "Documentation for Qt 6.8.0 GPLv3 components (QtVirtualKeyboard)",
  "Description": "Documentation for Qt 6.8.0 GPLv3 components (QtVirtualKeyboard)",
  "Version": "6.8.0-0-202408290438",
  "ReleaseDate": "2024-08-29",
  "Virtual": "true",
  "SortingPriority": "1",
  "DownloadableArchives": "qtvirtualkeyboard-documentation.zip",
  "CompressedSize": "2.3M",
  "UncompressedSize": "4.2M",
  "SHA1": "41be01dfd08b1cc97fac519240b4ee080cf4ef4e"
 },
 "qt.qt6.680.doc.qtwebchannel": {
  "Name": "qt.qt6.680.doc.qtwebchannel",
  "DisplayName": "Documentation for Qt 6.8.0 WebChannel",
  "Description": "Documentation for Qt 6.8.0 WebChannel",
  "Version": "6.8.0-0-202408290438",
  "ReleaseDate": "2024-08-29",
  "Virtual": "true",
  "SortingPriority": "1",
  "DownloadableArchives": "qtwebchannel-documentation.zip",
  "CompressedSize": "210.8K",
  "UncompressedSize": "436.5K",
  "SHA1": "e58b8946a058355f03e1a00649a7325a46393c35"
 },
 "qt.qt6.680.doc.qtwebsockets": {
  "Name": "qt.qt6.680.doc.qtwebsockets",
  "DisplayName": "Documentation for Qt 6.8.0 WebSockets",
  "Description": "Documentation for Qt 6.8.0 WebSockets",
  "Version": "6.8.0-0-202408290438",
  "ReleaseDate": "2024-08-29",
  "Virtual": "true",
  "SortingPriority": "1",
  "DownloadableArchives": "qtwebsockets-documentation.zip",
  "CompressedSize": "711.0K",
  "UncompressedSize": "1.2M",
  "SHA1": "9620c1d633ed6e3494ec2cd8885af0a80fc1e48d"
 },
 "qt.qt6.680.doc.qtwebview": {
  "Name": "qt.qt6.680.doc.qtwebview",
  "DisplayName": "Documentation for Qt 6.8.0 WebView",
  "Description": "Documentation for Qt 6.8.0 WebView",
  "Version": "6.8.0-0-202408290438",
  "ReleaseDate": "2024-08-29",
  "Virtual": "true",
  "SortingPriority": "1",
  "DownloadableArchives": "qtwebview-documentation.zip",
  "CompressedSize": "158.6K",
  "UncompressedSize": "309.2K",
  "SHA1": "677acbfd36284fd5b152111d106c54781f6561fd"
 },
 "qt.qt6.680.examples": {
  "Name": "qt.qt6.680.examples",
  "DisplayName": "Qt 6.8.0 Examples",
  "Description": "Qt 6.8.0 Examples",
  "Version": "6.8.0-0-202408290438",
  "ReleaseDate": "2024-08-29",
  "Dependencies": "qt.tools",
  "Virtual": "true",
  "Script": "installscript.qs",
  "SortingPriority": "1",
  "DownloadableArchives": "qtbase-examples-6.8.0-beta4.7z, qtdeclarative-examples-6.8.0-beta4.7z, qtdoc-examples-6.8.0-beta4.7z, qtsvg-examples-6.8.0-beta4.7z, qttools-examples-6.8.0-beta4.7z, qtwayland-examples-6.8.0-beta4.7z",
  "CompressedSize": "24.1M",
  "UncompressedSize": "41.8M",
  "SHA1": "7730a5e93f11078223a677bb265a6bd96d0d259d",
  "ArchiveSizes": {
   "qtwayland-examples-6.8.0-beta4.7z": "555K",
   "qttools-examples-6.8.0-beta4.7z": "458K",
   "qtsvg-examples-6.8.0-beta4.7z": "157",
   "qtdoc-examples-6.8.0-beta4.7z": "7.6M",
   "qtdeclarative-examples-6.8.0-beta4.7z": "11M",
   "qtbase-examples-6.8.0-beta4.7z": "4.1M"
  }
 },
 "qt.qt6.680.examples.qt3d": {
  "Name": "qt.qt6.680.examples.qt3d",
  "DisplayName": "Examples for Qt 6.8.0 3D",
  "Description": "Examples for Qt 6.8.0 3D",
  "Version": "6.8.0-0-202408290438",
  "ReleaseDate": "2024-08-29",
  "Virtual": "true",
  "SortingPriority": "1",
  "DownloadableArchives": "qt3d-examples-6.8.0-beta4.7z",
  "CompressedSize": "57.5M",
  "UncompressedSize": "65.0M",
  "SHA1": "7b875068151406d99ec7233b8062e6b7402bc4ab"
 },
 "qt.qt6.680.examples.qt5compat": {
  "Name": "qt.qt6.680.examples.qt5compat",
  "DisplayName": "Examples for Qt 6.8.0 Qt 5 Compatibility Module",
  "Description": "Examples for Qt 6.8.0 Qt 5 Compatibility Module",
  "Version": "6.8.0-0-202408290438",
  "ReleaseDate": "2024-08-29",
  "Virtual": "true",
  "SortingPriority": "1",
  "DownloadableArchives": "qt5compat-examples-6.8.0-beta4.7z",
  "CompressedSize": "27.4K",
  "UncompressedSize": "49.2K",
  "SHA1": "a47896a993b92843d775bca491cf96fae3e10d9f"
 },
 "qt.qt6.680.examples.qtactiveqt": {
  "Name": "qt.qt6.680.examples.qtactiveqt",
  "DisplayName": "Examples for Qt 6.8.0 Active Qt",
  "Description": "Examples for Qt 6.8.0 Active Qt",
  "Version": "6.8.0-0-202408290438",
  "ReleaseDate": "2024-08-29",
  "Virtual": "true",
  "SortingPriority": "1",
  "DownloadableArchives": "qtactiveqt-examples-6.8.0-beta4.7z",
  "CompressedSize": "11.8K",
  "UncompressedSize": "44.3K",
  "SHA1": "68800cb7e119f01e4f2c0bc1594fac952d0c0e23"
 },
 "qt.qt6.680.examples.qtcharts": {
  "Name": "qt.qt6.680.examples.qtcharts",
  "DisplayName": "Examples for Qt 6.8.0 GPLv3 components (QtCharts)",
  "Description": "Examples for Qt 6.8.0 GPLv3 components (QtCharts)",
  "Version": "6.8.0-0-202408290438",
  "ReleaseDate": "2024-08-29",
  "Virtual": "true",
  "SortingPriority": "1",
  "DownloadableArchives": "qtcharts-examples-6.8.0-beta4.7z",
  "CompressedSize": "159.1K",
  "UncompressedSize": "519.0K",
  "SHA1": "1cb262720a1a31e21080fe7ebd316e24dac11e7d"
 },
 "qt.qt6.680.examples.qtconnectivity": {
  "Name": "qt.qt6.680.examples.qtconnectivity",
  "DisplayName": "Examples for Qt 6.8.0 GPLv3 components (QtConnectivity)",
  "Description": "Examples for Qt 6.8.0 GPLv3 components (QtConnectivity)",
  "Version": "6.8.0-0-202408290438",
  "ReleaseDate": "2024-08-29",
  "Virtual": "true",
  "SortingPriority": "1",
  "DownloadableArchives": "qtconnectivity-examples-6.8.0-beta4.7z",
  "CompressedSize": "394.2K",
  "UncompressedSize": "613.1K",
  "SHA1": "073786def48e73cdf1a909ef0a745dd34283c514"
 },
 "qt.qt6.680.examples.qtdatavis3d": {
  "Name": "qt.qt6.680.examples.qtdatavis3d",
  "DisplayName": "Examples for Qt 6.8.0 GPLv3 components (QtDataVisualization)",
  "Description": "Examples for Qt 6.8.0 GPLv3 components (QtDataVisualization)",
  "Version": "6.8.0-0-202408290438",
  "ReleaseDate": "2024-08-29",
  "Virtual": "true",
  "SortingPriority": "1",
  "DownloadableArchives": "qtdatavis3d-examples-6.8.0-beta4.7z",
  "CompressedSize": "2.6M",
  "UncompressedSize": "3.2M",
  "SHA1": "2a4d7c69c040ba70388133c5eafb5195ad7ee306"
 },
 "qt.qt6.680.examples.qtgraphs": {
  "Name": "qt.qt6.680.examples.qtgraphs",
  "DisplayName": "Examples for Qt 6.8.0 GPLv3 components (QtGraphs)",
  "Description": "Examples for Qt 6.8.0 GPLv3 components (QtGraphs)",
  "Version": "6.8.0-0-202408290438",
  "ReleaseDate": "2024-08-29",
  "Virtual": "true",
  "SortingPriority": "1",
  "DownloadableArchives": "qtgraphs-examples-6.8.0-beta4.7z",
  "CompressedSize": "2.5M",
  "UncompressedSize": "3.3M",
  "SHA1": "a7f06a3fab37892629feddd6d41e38c7a52fa491"
 },
 "qt.qt6.680.examples.qtgrpc": {
  "Name": "qt.qt6.680.examples.qtgrpc",
  "DisplayName": "Examples for Qt 6.8.0 Protobuf and Qt 6.8.0 GRPC",
  "Description": "Examples for Qt 6.8.0 Protobuf and Qt 6.8.0 GRPC",
  "Version": "6.8.0-0-202408290438",
  "ReleaseDate": "2024-08-29",
  "Virtual": "true",
  "SortingPriority": "1",
  "DownloadableArchives": "qtgrpc-examples-6.8.0-beta4.7z",
  "CompressedSize": "102.4K",
  "UncompressedSize": "209.0K",
  "SHA1": "421c31d22e0c7f55bfd2198982ce1bf561db1984"
 },
 "qt.qt6.680.examples.qthttpserver": {
  "Name": "qt.qt6.680.examples.qthttpserver",
  "DisplayName": "Examples for Qt 6.8.0 HTTP Server",
  "Description": "Examples for Qt 6.8.0 HTTP Server ",
  "Version": "6.8.0-0-202408290438",
  "ReleaseDate": "2024-08-29",
  "Virtual": "true",
  "SortingPriority": "1",
  "DownloadableArchives": "qthttpserver-examples-6.8.0-beta4.7z",
  "CompressedSize": "50.6K",
  "UncompressedSize": "87.1K",
  "SHA1": "837036019a350966536298d4dbafd28551e9e00c"
 },
 "qt.qt6.680.examples.qtlocation": {
  "Name": "qt.qt6.680.examples.qtlocation",
  "DisplayName": "Examples for Qt 6.8.0 Location",
  "Description": "Examples for Qt 6.8.0 Location",
  "Version": "6.8.0-0-202408290438",
  "ReleaseDate": "2024-08-29",
  "Virtual": "true",
  "SortingPriority": "1",
  "DownloadableArchives": "qtlocation-examples-6.8.0-beta4.7z",
  "CompressedSize": "1.5M",
  "UncompressedSize": "3.8M",
  "SHA1": "ef503209e5c7fa326863d878335a41af8e463854"
 },
 "qt.qt6.680.examples.qtmultimedia": {
  "Name": "qt.qt6.680.examples.qtmultimedia",
  "DisplayName": "Examples for Qt Multimedia",
  "Description": "Examples for Qt Multimedia",
  "Version": "6.8.0-0-202408290438",
  "ReleaseDate": "2024-08-29",
  "Virtual": "true",
  "SortingPriority": "1",
  "DownloadableArchives": "qtmultimedia-examples-6.8.0-beta4.7z",
  "CompressedSize": "1.6M",
  "UncompressedSize": "2.4M",
  "SHA1": "e6ef7c1aef2929a2d0de520e6bb072e76130b1b0"
 },
 "qt.qt6.680.examples.qtnetworkauth": {
  "Name": "qt.qt6.680.examples.qtnetworkauth",
  "DisplayName": "Examples for Qt Networkauth (Technology Preview)",
  "Description": "Examples for Qt Networkauth (Technology Preview)",
  "Version": "6.8.0-0-202408290438",
  "ReleaseDate": "2024-08-29",
  "Virtual": "true",
  "SortingPriority": "1",
  "DownloadableArchives": "qtnetworkauth-examples-6.8.0-beta4.7z",
  "CompressedSize": "40.4K",
  "UncompressedSize": "48.0K",
  "SHA1": "293503bcd7bd2cadaff143c7fbe2bbb2ffe7eb42"
 },
 "qt.qt6.680.examples.qtpositioning": {
  "Name": "qt.qt6.680.examples.qtpositioning",
  "DisplayName": "Examples for Qt 6.8.0 GPLv3 components (QtPositioning)",
  "Description": "Examples for Qt 6.8.0 GPLv3 components (QtPositioning)",
  "Version": "6.8.0-0-202408290438",
  "ReleaseDate": "2024-08-29",
  "Virtual": "true",
  "SortingPriority": "1",
  "DownloadableArchives": "qtpositioning-examples-6.8.0-beta4.7z",
  "CompressedSize": "266.0K",
  "UncompressedSize": "604.5K",
  "SHA1": "5270dff07caac8838ebcaf655066f31cda1d9bdf"
 },
 "qt.qt6.680.examples.qtquick3d": {
  "Name": "qt.qt6.680.examples.qtquick3d",
  "DisplayName": "Examples for Qt 6.8.0 GPLv3 components (QtQuick3D)",
  "Description": "Examples for Qt 6.8.0 GPLv3 components (QtQuick3D)",
  "Version": "6.8.0-0-202408290438",
  "ReleaseDate": "2024-08-29",
  "Virtual": "true",
  "SortingPriority": "1",
  "DownloadableArchives": "qtquick3d-examples-6.8.0-beta4.7z",
  "CompressedSize": "20.3M",
  "UncompressedSize": "33.5M",
  "SHA1": "b4c011b18da017b66caf07f7c45b15505f29b03c"
 },
 "qt.qt6.680.examples.qtquick3dphysics": {
  "Name": "qt.qt6.680.examples.qtquick3dphysics",
  "DisplayName": "Examples for Qt 6.8.0 Quick: 3D Physics",
  "Description": "Examples for Qt 6.8.0 Quick: 3D Physics ",
  "Version": "6.8.0-0-202408290438",
  "ReleaseDate": "2024-08-29",
  "Virtual": "true",
  "SortingPriority": "1",
  "DownloadableArchives": "qtquick3dphysics-examples-6.8.0-beta4.7z",
  "CompressedSize": "2.2M",
  "UncompressedSize": "2.6M",
  "SHA1": "0468d930da2c9d44586a6212024118691671ccaa"
 },
 "qt.qt6.680.examples.qtquickeffectmaker": {
  "Name": "qt.qt6.680.examples.qtquickeffectmaker",
  "DisplayName": "Examples for Qt 6.8.0 Quick Effect Maker",
  "Description": "Examples for Qt 6.8.0 Quick Effect Maker",
  "Version": "6.8.0-0-202408290438",
  "ReleaseDate": "2024-08-29",
  "Virtual": "true",
  "SortingPriority": "1",
  "DownloadableArchives": "qtquickeffectmaker-examples-6.8.0-beta4.7z",
  "CompressedSize": "239.0K",
  "UncompressedSize": "268.4K",
  "SHA1": "40c30e0abe72e2436cc3cf8d2c359a15157e11ed"
 },
 "qt.qt6.680.examples.qtremoteobjects": {
  "Name": "qt.qt6.680.examples.qtremoteobjects",
  "DisplayName": "Examples for Qt Remote Objects",
  "Description": "Examples for Qt Remote Objects",
  "Version": "6.8.0-0-202408290438",
  "ReleaseDate": "2024-08-29",
  "Virtual": "true",
  "SortingPriority": "1",
  "DownloadableArchives": "qtremoteobjects-examples-6.8.0-beta4.7z",
  "CompressedSize": "79.8K",
  "UncompressedSize": "146.2K",
  "SHA1": "2b3baab97dfa5fbc42fee6fb8d756e385524c3fd"
 },
 "qt.qt6.680.examples.qtscxml": {
  "Name": "qt.qt6.680.examples.qtscxml",
  "DisplayName": "Examples for Qt 6.8.0 SCXML",
  "Description": "Examples for Qt 6.8.0 SCXML",
  "Version": "6.8.0-0-202408290438",
  "ReleaseDate": "2024-08-29",
  "Virtual": "true",
  "SortingPriority": "1",
  "DownloadableArchives": "qtscxml-examples-6.8.0-beta4.7z",
  "CompressedSize": "137.2K",
  "UncompressedSize": "291.8K",
  "SHA1": "c899da03f976fe99d277bcb1aaf705fc47ee5325"
 },
 "qt.qt6.680.examples.qtsensors": {
  "Name": "qt.qt6.680.examples.qtsensors",
  "DisplayName": "Examples for Qt 6.8.0 Sensors",
  "Description": "Examples for Qt 6.8.0 Sensors",
  "Version": "6.8.0-0-202408290438",
  "ReleaseDate": "2024-08-29",
  "Virtual": "true",
  "SortingPriority": "1",
  "DownloadableArchives": "qtsensors-examples-6.8.0-beta4.7z",
  "CompressedSize": "52.3K",
  "UncompressedSize": "95.6K",
  "SHA1": "269d8bfb95ba3124cf9b2814dfc0c7d56d0b1390"
 },
 "qt.qt6.680.examples.qtserialbus": {
  "Name": "qt.qt6.680.examples.qtserialbus",
  "DisplayName": "Examples for Qt SerialBus",
  "Description": "Examples for Qt SerialBus",
  "Version": "6.8.0-0-202408290438",
  "ReleaseDate": "2024-08-29",
  "Virtual": "true",
  "SortingPriority": "1",
  "DownloadableArchives": "qtserialbus-examples-6.8.0-beta4.7z",
  "CompressedSize": "207.2K",
  "UncompressedSize": "569.1K",
  "SHA1": "e4b20c010f09e404944acf67cfe72f2890a55c97"
 },
 "qt.qt6.680.examples.qtserialport": {
  "Name": "qt.qt6.680.examples.qtserialport",
  "DisplayName": "Examples for Qt SerialPort",
  "Description": "Examples for Qt SerialPort",
  "Version": "6.8.0-0-202408290438",
  "ReleaseDate": "2024-08-29",
  "Virtual": "true",
  "SortingPriority": "1",
  "DownloadableArchives": "qtserialport-examples-6.8.0-beta4.7z",
  "CompressedSize": "79.2K",
  "UncompressedSize": "136.3K",
  "SHA1": "30d12469eb2a038a3a5cdecb241c4c425a09c9d7"
 },
 "qt.qt6.680.examples.qtspeech": {
  "Name": "qt.qt6.680.examples.qtspeech",
  "DisplayName": "Examples for Qt Speech (Technology Preview)",
  "Description": "Examples for Qt Speech (Technology Preview)",
  "Version": "6.8.0-0-202408290438",
  "ReleaseDate": "2024-08-29",
  "Virtual": "true",
  "SortingPriority": "1",
  "DownloadableArchives": "qtspeech-examples-6.8.0-beta4.7z",
  "CompressedSize": "154.1K",
  "UncompressedSize": "190.6K",
  "SHA1": "fbd9b1b5863c4cfdfeb00c253b8c97afaa4c78c6"
 },
 "qt.qt6.680.examples.qtvirtualkeyboard": {
  "Name": "qt.qt6.680.examples.qtvirtualkeyboard",
  "DisplayName": "Examples for Qt 6.8.0 GPLv3 components (QtVirtualKeyboard)",
  "Description": "Examples for Qt 6.8.0 GPLv3 components (QtVirtualKeyboard)",
  "Version": "6.8.0-0-202408290438",
  "ReleaseDate": "2024-08-29",
  "Virtual": "true",
  "SortingPriority": "1",
  "DownloadableArchives": "qtvirtualkeyboard-examples-6.8.0-beta4.7z",
  "CompressedSize": "6.9K",
  "UncompressedSize": "31.0K",
  "SHA1": "14cb79b27e16d3a858f4e83af22582da3655e5d4"
 },
 "qt.qt6.680.examples.qtwebchannel": {
  "Name": "qt.qt6.680.examples.qtwebchannel",
  "DisplayName": "Examples for Qt 6.8.0 WebChannel",
  "Description": "Examples for Qt 6.8.0 WebChannel",
  "Version": "6.8.0-0-202408290438",
  "ReleaseDate": "2024-08-29",
  "Virtual": "true",
  "SortingPriority": "1",
  "DownloadableArchives": "qtwebchannel-examples-6.8.0-beta4.7z",
  "CompressedSize": "64.7K",
  "UncompressedSize": "119.9K",
  "SHA1": "af076bd6580daf776f534ad72cbdf5431f56bd51"
 },
 "qt.qt6.680.examples.qtwebsockets": {
  "Name": "qt.qt6.680.examples.qtwebsockets",
  "DisplayName": "Examples for Qt 6.8.0 WebSockets",
  "Description": "Examples for Qt 6.8.0 WebSockets",
  "Version": "6.8.0-0-202408290438",
  "ReleaseDate": "2024-08-29",
  "Virtual": "true",
  "SortingPriority": "1",
  "DownloadableArchives": "qtwebsockets-examples-6.8.0-beta4.7z",
  "CompressedSize": "243.2K",
  "UncompressedSize": "292.5K",
  "SHA1": "29e893f1ee54c4223e69d370802de16c2c6987a5"
 },
 "qt.qt6.680.examples.qtwebview": {
  "Name": "qt.qt6.680.examples.qtwebview",
  "DisplayName": "Examples for Qt 6.8.0 WebView",
  "Description": "Examples for Qt 6.8.0 WebView",
  "Version": "6.8.0-0-202408290438",
  "ReleaseDate": "2024-08-29",
  "Virtual": "true",
  "SortingPriority": "1",
  "DownloadableArchives": "qtwebview-examples-6.8.0-beta4.7z",
  "CompressedSize": "46.2K",
  "UncompressedSize": "60.5K",
  "SHA1": "a125180410badf8086fe5b084977bf053a61fcbd"
 },
 "qt.qt6.680.src": {
  "Name": "qt.qt6.680.src",
  "DisplayName": "Sources",
  "Description": "Qt 6.8.0 Source Components",
  "Version": "6.8.0-0-202408290438",
  "ReleaseDate": "2024-08-29",
  "SortingPriority": "100",
  "DownloadableArchives": "qtdoc-everywhere-src-6.8.0-beta4.zip, qtwayland-everywhere-src-6.8.0-beta4.zip, qtbase-everywhere-src-6.8.0-beta4.zip, qtsvg-everywhere-src-6.8.0-beta4.zip, qtdeclarative-everywhere-src-6.8.0-beta4.zip, qttools-everywhere-src-6.8.0-beta4.zip, qt5compat-everywhere-src-6.8.0-beta4.zip, qtshadertools-everywhere-src-6.8.0-beta4.zip, qtquick3d-everywhere-src-6.8.0-beta4.zip, qtquick3dphysics-everywhere-src-6.8.0-beta4.zip, qtquickeffectmaker-everywhere-src-6.8.0-beta4.zip, qtquicktimeline-everywhere-src-6.8.0-beta4.zip, qttranslations-everywhere-src-6.8.0-beta4.zip, qt5-everywhere-src-6.8.0-beta4.zip, qt3d-everywhere-src-6.8.0-beta4.zip, qtactiveqt-everywhere-src-6.8.0-beta4.zip, qtcharts-everywhere-src-6.8.0-beta4.zip, qtcoap-everywhere-src-6.8.0-beta4.zip, qtconnectivity-everywhere-src-6.8.0-beta4.zip, qtdatavis3d-everywhere-src-6.8.0-beta4.zip, qtgraphs-everywhere-src-6.8.0-beta4.zip, qtgrpc-everywhere-src-6.8.0-beta4.zip, qthttpserver-everywhere-src-6.8.0-beta4.zip, qtimageformats-everywhere-src-6.8.0-beta4.zip, qtlanguageserver-everywhere-src-6.8.0-beta4.zip, qtlocation-everywhere-src-6.8.0-beta4.zip, qtlottie-everywhere-src-6.8.0-beta4.zip, qtmqtt-everywhere-src-6.8.0-beta4.zip, qtmultimedia-everywhere-src-6.8.0-beta4.zip, qtnetworkauth-everywhere-src-6.8.0-beta4.zip, qtopcua-everywhere-src-6.8.0-beta4.zip, qtpositioning-everywhere-src-6.8.0-beta4.zip, qtremoteobjects-everywhere-src-6.8.0-beta4.zip, qtscxml-everywhere-src-6.8.0-beta4.zip, qtsensors-everywhere-src-6.8.0-beta4.zip, qtserialbus-everywhere-src-6.8.0-beta4.zip, qtserialport-everywhere-src-6.8.0-beta4.zip, qtspeech-everywhere-src-6.8.0-beta4.zip, qtvirtualkeyboard-everywhere-src-6.8.0-beta4.zip, qtwebchannel-everywhere-src-6.8.0-beta4.zip, qtwebsockets-everywhere-src-6.8.0-beta4.zip, qtwebview-everywhere-src-6.8.0-beta4.zip",
  "CompressedSize": "524.4M",
  "UncompressedSize": "988.0M",
  "SHA1": "47351930355689e4da212251e184eb254decfd5a",
  "ArchiveSizes": {}
 }
}