{
 "qt.tools.qtcreator.telemetry": {
  "Name": "qt.tools.qtcreator.telemetry",
  "DisplayName": "Qt Telemetry plugin",
  "Description": "Collects pseudonymous data from Qt Creator",
  "Version": "9.0.0-0-202211220359",
  "ReleaseDate": "2022-11-22",
  "Script": "installscript.qs",
  "Virtual": "true",
  "Replaces": "qt.tools.qtcreator.telemetry_evaluator",
  "AutoDependOn": null,
  "CompressedSize": "122.4K",
  "UncompressedSize": "663.9K",
  "DownloadableArchives": "telemetry.7z",
  "UserInterfaces": "telemetrypluginform.ui",
  "Translations": "de.qm,pt.qm,ar.qm,ja.qm,fr.qm,ru.qm,es.qm",
  "SHA1": "e6854d9822d9748079236ddc488c61dfb591ecc8"
 }
}